{
  "Date": "2024-11-20",
  "AUD": 1.6225,
  "BRL": 6.0975,
  "CAD": 1.4767,
  "CHF": 0.9342,
  "CNY": 7.6528,
  "CZK": 25.286,
  "DKK": 7.4592,
  "GBP": 0.8338,
  "HKD": 8.2208,
  "HUF": 409.6,
  "IDR": 16790.04,
  "ILS": 3.9413,
  "100 paise": 89.1025,
  "ISK": 145.5,
  "JPY": 164.42,
  "KRW": 1474.4,
  "MXN": 21.3036,
  "MYR": 4.7228,
  "NOK": 11.644,
  "NZD": 1.7947,
  "PHP": 62.282,
  "PLN": 4.3308,
  "RON": 4.9765,
  "RUB": "",
  "SEK": 11.605,
  "SGD": 1.4173,
  "THB": 36.581,
  "TRY": 36.4025,
  "USD": 1.0562,
  "ZAR": 19.1266
}