{
  "Date": "2024-07-10",
  "AUD": 1.6056,
  "BGN": 1.9558,
  "BRL": 5.8435,
  "CAD": 1.4758,
  "CHF": 0.9723,
  "CNY": 7.8763,
  "CYP": "",
  "CZK": 25.379,
  "DKK": 7.4603,
  "EEK": "",
  "GBP": 0.84518,
  "HKD": 8.4554,
  "HUF": 392.68,
  "IDR": 17557.93,
  "ILS": 3.9574,
  "100 paise": 90.4015,
  "ISK": 149.1,
  "JPY": 174.79,
  "KRW": 1498.46,
  "LTL": "",
  "LVL": "",
  "MTL": "",
  "MXN": 19.2904,
  "MYR": 5.0883,
  "NOK": 11.607,
  "NZD": 1.7804,
  "PHP": 63.118,
  "PLN": 4.2555,
  "RON": 4.9734,
  "RUB": "",
  "SEK": 11.4075,
  "SGD": 1.4605,
  "SIT": "",
  "SKK": "",
  "THB": 39.343,
  "TRY": 35.5705,
  "USD": 1.0825,
  "ZAR": 19.5581
}