{
  "Date": "2024-11-19",
  "AUD": 1.6264,
  "BGN": 1.9558,
  "BRL": 6.1212,
  "CAD": 1.4833,
  "CHF": 0.9329,
  "CNY": 7.6578,
  "CZK": 25.284,
  "DKK": 7.4591,
  "GBP": 0.83638,
  "HKD": 8.2335,
  "HUF": 407.45,
  "IDR": 16759.52,
  "ILS": 3.9611,
  "100 paise": 89.2935,
  "ISK": 145.3,
  "JPY": 162.71,
  "KRW": 1472.84,
  "MXN": 21.4956,
  "MYR": 4.7315,
  "NOK": 11.6595,
  "NZD": 1.7949,
  "PHP": 62.314,
  "PLN": 4.3303,
  "RON": 4.9769,
  "RUB": "",
  "SEK": 11.584,
  "SGD": 1.4163,
  "THB": 36.521,
  "TRY": 36.5558,
  "USD": 1.0578,
  "ZAR": 19.097
}