{
  "Date": "2025-05-07",
  "AUD": 1.7553,
  "BGN": 1.9558,
  "BRL": 6.4763,
  "CAD": 1.5673,
  "CHF": 0.9359,
  "CNY": 8.2079,
  "CYP": "",
  "CZK": 24.924,
  "DKK": 7.4615,
  "EEK": "",
  "GBP": 0.8511,
  "HKD": 8.8139,
  "HUF": 404.08,
  "IDR": 18762.86,
  "ILS": 4.0717,
  "100 paise": 96.2925,
  "ISK": 146.3,
  "JPY": 162.89,
  "KRW": 1580.35,
  "LTL": "",
  "LVL": "",
  "MTL": "",
  "MXN": 22.3014,
  "MYR": 4.8155,
  "NOK": 11.6715,
  "NZD": 1.8979,
  "PHP": 62.889,
  "PLN": 4.2753,
  "RON": 5.109,
  "RUB": "",
  "SEK": 10.903,
  "SGD": 1.467,
  "SIT": "",
  "SKK": "",
  "THB": 37.147,
  "TRY": 43.8992,
  "USD": 1.136,
  "ZAR": 20.7755
}