{
  "Date": "2025-03-13",
  "AUD": 1.7264,
  "BGN": 1.9558,
  "BRL": 6.3032,
  "CAD": 1.5591,
  "CHF": 0.9579,
  "CNY": 7.8493,
  "CZK": 25.093,
  "DKK": 7.4605,
  "GBP": 0.83778,
  "HKD": 8.4175,
  "HUF": 400.28,
  "IDR": 17799.48,
  "ILS": 3.9622,
  "100 paise": 94.27,
  "ISK": 146.1,
  "JPY": 160.64,
  "KRW": 1577.63,
  "LTL": "",
  "LVL": "",
  "MXN": 21.8318,
  "MYR": 4.8064,
  "NOK": 11.5975,
  "NZD": 1.9045,
  "PHP": 62.238,
  "PLN": 4.1965,
  "RON": 4.9775,
  "RUB": "",
  "SEK": 11.07,
  "SGD": 1.4484,
  "SIT": "",
  "THB": 36.665,
  "TRY": 39.6459,
  "USD": 1.083,
  "ZAR": 19.9578
}