{
  "Date": "2024-11-07",
  "AUD": 1.6196,
  "BGN": 1.9558,
  "BRL": 6.0988,
  "CAD": 1.496,
  "CHF": 0.9432,
  "CNY": 7.7159,
  "CYP": "",
  "CZK": 25.262,
  "DKK": 7.4574,
  "EEK": "",
  "GBP": 0.83185,
  "HKD": 8.3818,
  "HUF": 404.58,
  "IDR": 16889.15,
  "ILS": 4.0094,
  "100 paise": 90.9355,
  "ISK": 148.3,
  "JPY": 165.71,
  "KRW": 1495.78,
  "LTL": "",
  "LVL": "",
  "MTL": "",
  "MXN": 21.3897,
  "MYR": 4.7492,
  "NOK": 11.7485,
  "NZD": 1.7932,
  "PHP": 63.1,
  "PLN": 4.3253,
  "RON": 4.9759,
  "RUB": "",
  "SEK": 11.599,
  "SGD": 1.4258,
  "SIT": "",
  "SKK": "",
  "THB": 36.798,
  "TRY": 36.9319,
  "USD": 1.0785,
  "ZAR": 18.7328
}